pretzel/task.py
pretzel/bench.py
pretzel/event.py
pretzel/state_machine.py
pretzel/boot.py
pretzel/dispose.py
pretzel/uniform.py
pretzel/app.py
pretzel/console.py
pretzel/log.py
pretzel/process.py
pretzel/utils.py
pretzel/__init__.py
pretzel/apps/__init__.py
pretzel/apps/shell.py
pretzel/core/tests.py
pretzel/core/core.py
pretzel/core/poll.py
pretzel/core/__init__.py
pretzel/monad/ident.py
pretzel/monad/proxy.py
pretzel/monad/cont.py
pretzel/monad/do_green.py
pretzel/monad/list.py
pretzel/monad/__init__.py
pretzel/monad/async.py
pretzel/monad/monad.py
pretzel/monad/do.py
pretzel/monad/result.py
pretzel/monad/tests/__init__.py
pretzel/monad/tests/do_green.py
pretzel/monad/tests/monad.py
pretzel/monad/tests/async.py
pretzel/remoting/__init__.py
pretzel/remoting/bench.py
pretzel/remoting/closure.py
pretzel/remoting/expr.py
pretzel/remoting/hub.py
pretzel/remoting/importer.py
pretzel/remoting/proxy.py
pretzel/remoting/conn/__init__.py
pretzel/remoting/conn/composite.py
pretzel/remoting/conn/stream.py
pretzel/remoting/conn/fork.py
pretzel/remoting/conn/shell.py
pretzel/remoting/conn/ssh.py
pretzel/remoting/conn/conn.py
pretzel/remoting/tests/__init__.py
pretzel/remoting/tests/closure.py
pretzel/remoting/tests/composite.py
pretzel/remoting/tests/conn_int.py
pretzel/remoting/tests/hub.py
pretzel/remoting/tests/conn.py
pretzel/remoting/tests/expr.py
pretzel/remoting/tests/proxy.py
pretzel/store/__init__.py
pretzel/store/store.py
pretzel/store/stream.py
pretzel/store/alloc.py
pretzel/store/serialize.py
pretzel/store/map/__init__.py
pretzel/store/map/bptree.py
pretzel/store/map/map.py
pretzel/store/map/provider/__init__.py
pretzel/store/map/provider/memory.py
pretzel/store/map/provider/provider.py
pretzel/store/map/provider/store.py
pretzel/store/tests/__init__.py
pretzel/store/tests/alloc.py
pretzel/store/tests/bptree.py
pretzel/store/tests/serialize.py
pretzel/store/tests/store.py
pretzel-1.0.10.dist-info/top_level.txt
pretzel-1.0.10.dist-info/METADATA
pretzel-1.0.10.dist-info/DESCRIPTION.rst
pretzel-1.0.10.dist-info/pydist.json
pretzel-1.0.10.dist-info/WHEEL
pretzel-1.0.10.dist-info/RECORD
