Metadata-Version: 2.0
Name: pretzel
Version: 1.0.10
Summary: Pretzel - asynchronous python framework
Home-page: https://github.com/aslpavel/pretzel
Author: Pavel Aslanov
Author-email: asl.pavel@gmail.com
License: Apache License 2.0
Platform: UNKNOWN
